{
    "version": "5.4.1",
    "flags": {},
    "shapes": [
        {
            "label": "truck",
            "points": [
                [
                    656.814208984375,
                    177.96002197265625
                ],
                [
                    845.598876953125,
                    443.15771484375
                ]
            ],
            "group_id": null,
            "description": "",
            "shape_type": "rectangle",
            "flags": {},
            "mask": null
        },
        {
            "label": "truck",
            "points": [
                [
                    1042.323486328125,
                    109.61181640625
                ],
                [
                    1279.895751953125,
                    523.2420654296875
                ]
            ],
            "group_id": null,
            "description": "",
            "shape_type": "rectangle",
            "flags": {},
            "mask": null
        },
        {
            "label": "rider",
            "points": [
                [
                    102.11001586914062,
                    343.7337646484375
                ],
                [
                    145.65879821777344,
                    441.15484619140625
                ]
            ],
            "group_id": null,
            "description": "",
            "shape_type": "rectangle",
            "flags": {},
            "mask": null
        },
        {
            "label": "car",
            "points": [
                [
                    989.1689453125,
                    322.11468505859375
                ],
                [
                    1052.122314453125,
                    414.65203857421875
                ]
            ],
            "group_id": null,
            "description": "",
            "shape_type": "rectangle",
            "flags": {},
            "mask": null
        },
        {
            "label": "motorcycle",
            "points": [
                [
                    46.50129699707031,
                    366.4243469238281
                ],
                [
                    147.41763305664062,
                    420.0672912597656
                ]
            ],
            "group_id": null,
            "description": "",
            "shape_type": "rectangle",
            "flags": {},
            "mask": null
        },
        {
            "label": "car",
            "points": [
                [
                    858.1414794921875,
                    331.62445068359375
                ],
                [
                    976.6715087890625,
                    382.68280029296875
                ]
            ],
            "group_id": null,
            "description": "",
            "shape_type": "rectangle",
            "flags": {},
            "mask": null
        }
    ],
    "imagePath": "Sequence_Day_7_frame_47910.jpg",
    "imageData": null,
    "imageHeight": 720,
    "imageWidth": 1280
}