{
    "version": "5.4.1",
    "flags": {},
    "shapes": [
        {
            "label": "person",
            "points": [
                [
                    830.9075927734375,
                    241.3824462890625
                ],
                [
                    957.2193603515625,
                    579.311767578125
                ]
            ],
            "group_id": null,
            "description": "",
            "shape_type": "rectangle",
            "flags": {},
            "mask": null
        },
        {
            "label": "car",
            "points": [
                [
                    665.2366333007812,
                    328.059326171875
                ],
                [
                    719.3641967773438,
                    356.73046875
                ]
            ],
            "group_id": null,
            "description": "",
            "shape_type": "rectangle",
            "flags": {},
            "mask": null
        },
        {
            "label": "car",
            "points": [
                [
                    426.68658447265625,
                    328.1189880371094
                ],
                [
                    478.09906005859375,
                    365.5586853027344
                ]
            ],
            "group_id": null,
            "description": "",
            "shape_type": "rectangle",
            "flags": {},
            "mask": null
        },
        {
            "label": "person",
            "points": [
                [
                    773.061767578125,
                    260.7120361328125
                ],
                [
                    830.8768310546875,
                    531.14013671875
                ]
            ],
            "group_id": null,
            "description": "",
            "shape_type": "rectangle",
            "flags": {},
            "mask": null
        },
        {
            "label": "car",
            "points": [
                [
                    1185.19482421875,
                    310.550048828125
                ],
                [
                    1280.0,
                    473.89923095703125
                ]
            ],
            "group_id": null,
            "description": "",
            "shape_type": "rectangle",
            "flags": {},
            "mask": null
        },
        {
            "label": "truck",
            "points": [
                [
                    341.5565185546875,
                    281.4360046386719
                ],
                [
                    405.2568359375,
                    372.1529235839844
                ]
            ],
            "group_id": null,
            "description": "",
            "shape_type": "rectangle",
            "flags": {},
            "mask": null
        },
        {
            "label": "person",
            "points": [
                [
                    792.9019775390625,
                    271.23748779296875
                ],
                [
                    861.9786376953125,
                    548.5823974609375
                ]
            ],
            "group_id": null,
            "description": "",
            "shape_type": "rectangle",
            "flags": {},
            "mask": null
        },
        {
            "label": "person",
            "points": [
                [
                    462.2132263183594,
                    316.312255859375
                ],
                [
                    485.1470642089844,
                    368.9898681640625
                ]
            ],
            "group_id": null,
            "description": "",
            "shape_type": "rectangle",
            "flags": {},
            "mask": null
        },
        {
            "label": "bus",
            "points": [
                [
                    0.0,
                    0.0
                ],
                [
                    334.07635498046875,
                    623.3031005859375
                ]
            ],
            "group_id": null,
            "description": "",
            "shape_type": "rectangle",
            "flags": {},
            "mask": null
        },
        {
            "label": "truck",
            "points": [
                [
                    0.034515380859375,
                    0.0
                ],
                [
                    335.0356750488281,
                    611.96337890625
                ]
            ],
            "group_id": null,
            "description": "",
            "shape_type": "rectangle",
            "flags": {},
            "mask": null
        },
        {
            "label": "car",
            "points": [
                [
                    403.0966796875,
                    329.8670959472656
                ],
                [
                    428.31298828125,
                    357.3433532714844
                ]
            ],
            "group_id": null,
            "description": "",
            "shape_type": "rectangle",
            "flags": {},
            "mask": null
        },
        {
            "label": "car",
            "points": [
                [
                    1138.0604248046875,
                    329.80560302734375
                ],
                [
                    1249.5328369140625,
                    420.8575439453125
                ]
            ],
            "group_id": null,
            "description": "",
            "shape_type": "rectangle",
            "flags": {},
            "mask": null
        }
    ],
    "imagePath": "Sequence_Day_7_frame_19260.jpg",
    "imageData": null,
    "imageHeight": 720,
    "imageWidth": 1280
}