{
    "version": "5.4.1",
    "flags": {},
    "shapes": [
        {
            "label": "truck",
            "points": [
                [
                    469.7439880371094,
                    208.9496307373047
                ],
                [
                    591.9832763671875,
                    392.86260986328125
                ]
            ],
            "group_id": null,
            "description": "",
            "shape_type": "rectangle",
            "flags": {},
            "mask": null
        },
        {
            "label": "car",
            "points": [
                [
                    97.35415649414062,
                    286.7763671875
                ],
                [
                    172.1612548828125,
                    371.4342041015625
                ]
            ],
            "group_id": null,
            "description": "",
            "shape_type": "rectangle",
            "flags": {},
            "mask": null
        },
        {
            "label": "truck",
            "points": [
                [
                    357.0671691894531,
                    249.6427001953125
                ],
                [
                    450.4510803222656,
                    344.60589599609375
                ]
            ],
            "group_id": null,
            "description": "",
            "shape_type": "rectangle",
            "flags": {},
            "mask": null
        },
        {
            "label": "person",
            "points": [
                [
                    306.9617919921875,
                    299.7225341796875
                ],
                [
                    324.37060546875,
                    336.82958984375
                ]
            ],
            "group_id": null,
            "description": "",
            "shape_type": "rectangle",
            "flags": {},
            "mask": null
        },
        {
            "label": "truck",
            "points": [
                [
                    0.0,
                    9.3468017578125
                ],
                [
                    103.1572265625,
                    536.8779296875
                ]
            ],
            "group_id": null,
            "description": "",
            "shape_type": "rectangle",
            "flags": {},
            "mask": null
        },
        {
            "label": "car",
            "points": [
                [
                    884.419677734375,
                    313.81475830078125
                ],
                [
                    926.043701171875,
                    341.72430419921875
                ]
            ],
            "group_id": null,
            "description": "",
            "shape_type": "rectangle",
            "flags": {},
            "mask": null
        }
    ],
    "imagePath": "Sequence_Day_7_frame_0.jpg",
    "imageData": null,
    "imageHeight": 720,
    "imageWidth": 1280
}