{
    "version": "5.6.0",
    "flags": {},
    "shapes": [
        {
            "label": "car",
            "points": [
                [
                    807.724609375,
                    471.83172607421875
                ],
                [
                    909.5908203125,
                    561.0980834960938
                ]
            ],
            "group_id": null,
            "description": "",
            "shape_type": "rectangle",
            "flags": {},
            "mask": null
        },
        {
            "label": "truck",
            "points": [
                [
                    851.3619384765625,
                    442.086669921875
                ],
                [
                    923.6597900390625,
                    518.5804443359375
                ]
            ],
            "group_id": null,
            "description": "",
            "shape_type": "rectangle",
            "flags": {},
            "mask": null
        },
        {
            "label": "car",
            "points": [
                [
                    521.3695068359375,
                    500.37945556640625
                ],
                [
                    616.2694091796875,
                    536.2295532226562
                ]
            ],
            "group_id": null,
            "description": "",
            "shape_type": "rectangle",
            "flags": {},
            "mask": null
        },
        {
            "label": "truck",
            "points": [
                [
                    0.059906005859375,
                    377.146728515625
                ],
                [
                    396.46636962890625,
                    719.614501953125
                ]
            ],
            "group_id": null,
            "description": "",
            "shape_type": "rectangle",
            "flags": {},
            "mask": null
        },
        {
            "label": "truck",
            "points": [
                [
                    789.7021484375,
                    461.58734130859375
                ],
                [
                    840.222412109375,
                    508.28485107421875
                ]
            ],
            "group_id": null,
            "description": "",
            "shape_type": "rectangle",
            "flags": {},
            "mask": null
        },
        {
            "label": "truck",
            "points": [
                [
                    615.0,
                    449.8148148148148
                ],
                [
                    750.1851851851852,
                    579.4444444444445
                ]
            ],
            "group_id": null,
            "description": "",
            "shape_type": "rectangle",
            "flags": {},
            "mask": null
        }
    ],
    "imagePath": "Sequence_Day_3_frame_12090.jpg",
    "imageData": null,
    "imageHeight": 720,
    "imageWidth": 1280
}