{
    "version": "5.6.0",
    "flags": {},
    "shapes": [
        {
            "label": "bus",
            "points": [
                [
                    698.6871337890625,
                    307.027587890625
                ],
                [
                    879.46875,
                    471.94140625
                ]
            ],
            "group_id": null,
            "description": "",
            "shape_type": "rectangle",
            "flags": {},
            "mask": null
        },
        {
            "label": "bus",
            "points": [
                [
                    0.769805908203125,
                    333.83807373046875
                ],
                [
                    327.5223083496094,
                    452.31866455078125
                ]
            ],
            "group_id": null,
            "description": "",
            "shape_type": "rectangle",
            "flags": {},
            "mask": null
        },
        {
            "label": "motorcycle",
            "points": [
                [
                    444.98541259765625,
                    410.2748107910156
                ],
                [
                    474.06488037109375,
                    460.1153259277344
                ]
            ],
            "group_id": null,
            "description": "",
            "shape_type": "rectangle",
            "flags": {},
            "mask": null
        },
        {
            "label": "bus",
            "points": [
                [
                    456.231689453125,
                    348.5757141113281
                ],
                [
                    516.1014404296875,
                    432.2059020996094
                ]
            ],
            "group_id": null,
            "description": "",
            "shape_type": "rectangle",
            "flags": {},
            "mask": null
        },
        {
            "label": "car",
            "points": [
                [
                    1261.649169921875,
                    405.3323669433594
                ],
                [
                    1280.0,
                    478.8803405761719
                ]
            ],
            "group_id": null,
            "description": "",
            "shape_type": "rectangle",
            "flags": {},
            "mask": null
        },
        {
            "label": "rider",
            "points": [
                [
                    447.05780029296875,
                    382.3790283203125
                ],
                [
                    475.06378173828125,
                    451.20703125
                ]
            ],
            "group_id": null,
            "description": "",
            "shape_type": "rectangle",
            "flags": {},
            "mask": null
        },
        {
            "label": "motorcycle",
            "points": [
                [
                    976.3131103515625,
                    415.3575439453125
                ],
                [
                    1012.1934814453125,
                    448.32421875
                ]
            ],
            "group_id": null,
            "description": "",
            "shape_type": "rectangle",
            "flags": {},
            "mask": null
        },
        {
            "label": "motorcycle",
            "points": [
                [
                    398.2716369628906,
                    405.0360107421875
                ],
                [
                    438.0401306152344,
                    448.0655517578125
                ]
            ],
            "group_id": null,
            "description": "",
            "shape_type": "rectangle",
            "flags": {},
            "mask": null
        },
        {
            "label": "person",
            "points": [
                [
                    881.6033935546875,
                    399.9339599609375
                ],
                [
                    898.8221435546875,
                    444.3740234375
                ]
            ],
            "group_id": null,
            "description": "",
            "shape_type": "rectangle",
            "flags": {},
            "mask": null
        },
        {
            "label": "car",
            "points": [
                [
                    491.29815673828125,
                    337.7606201171875
                ],
                [
                    661.4048461914062,
                    529.200439453125
                ]
            ],
            "group_id": null,
            "description": "",
            "shape_type": "rectangle",
            "flags": {},
            "mask": null
        },
        {
            "label": "person",
            "points": [
                [
                    108.46906519647864,
                    396.2026166773554
                ],
                [
                    124.70149253731344,
                    464.8507462686567
                ]
            ],
            "group_id": null,
            "description": "",
            "shape_type": "rectangle",
            "flags": {},
            "mask": null
        },
        {
            "label": "person",
            "points": [
                [
                    41.30488609200101,
                    385.75485548332557
                ],
                [
                    67.23880597014926,
                    435.0
                ]
            ],
            "group_id": null,
            "description": "",
            "shape_type": "rectangle",
            "flags": {},
            "mask": null
        },
        {
            "label": "person",
            "points": [
                [
                    69.66309504722489,
                    390.23246742362403
                ],
                [
                    85.1492537313433,
                    417.08955223880594
                ]
            ],
            "group_id": null,
            "description": "",
            "shape_type": "rectangle",
            "flags": {},
            "mask": null
        },
        {
            "label": "person",
            "points": [
                [
                    81.60339355468761,
                    396.20261667735537
                ],
                [
                    112.76119402985076,
                    416.3432835820895
                ]
            ],
            "group_id": null,
            "description": "",
            "shape_type": "rectangle",
            "flags": {},
            "mask": null
        }
    ],
    "imagePath": "Sequence_Day_10_frame_13350.jpg",
    "imageData": null,
    "imageHeight": 720,
    "imageWidth": 1280
}