{
    "version": "5.6.0",
    "flags": {},
    "shapes": [
        {
            "label": "truck",
            "points": [
                [
                    632.1101684570312,
                    269.30145263671875
                ],
                [
                    965.4658813476562,
                    607.1688842773438
                ]
            ],
            "group_id": null,
            "description": "",
            "shape_type": "rectangle",
            "flags": {},
            "mask": null
        },
        {
            "label": "motorcycle",
            "points": [
                [
                    564.364990234375,
                    407.9383544921875
                ],
                [
                    600.55859375,
                    448.5576171875
                ]
            ],
            "group_id": null,
            "description": "",
            "shape_type": "rectangle",
            "flags": {},
            "mask": null
        },
        {
            "label": "rider",
            "points": [
                [
                    567.1735229492188,
                    378.6728820800781
                ],
                [
                    598.4841918945312,
                    440.4479675292969
                ]
            ],
            "group_id": null,
            "description": "",
            "shape_type": "rectangle",
            "flags": {},
            "mask": null
        },
        {
            "label": "person",
            "points": [
                [
                    525.9685668945312,
                    380.197998046875
                ],
                [
                    549.1995239257812,
                    454.4583740234375
                ]
            ],
            "group_id": null,
            "description": "",
            "shape_type": "rectangle",
            "flags": {},
            "mask": null
        },
        {
            "label": "motorcycle",
            "points": [
                [
                    122.17054263565892,
                    427.8294573643411
                ],
                [
                    253.95348837209303,
                    543.3333333333333
                ]
            ],
            "group_id": null,
            "description": "",
            "shape_type": "rectangle",
            "flags": {},
            "mask": null
        },
        {
            "label": "traffic sign",
            "points": [
                [
                    446.9767441860465,
                    355.73643410852713
                ],
                [
                    475.6589147286822,
                    377.4418604651163
                ]
            ],
            "group_id": null,
            "description": "",
            "shape_type": "rectangle",
            "flags": {},
            "mask": null
        }
    ],
    "imagePath": "Sequence_Day_10_frame_8730.jpg",
    "imageData": null,
    "imageHeight": 720,
    "imageWidth": 1280
}