{
    "version": "5.6.0",
    "flags": {},
    "shapes": [
        {
            "label": "rider",
            "points": [
                [
                    465.9462890625,
                    364.09149169921875
                ],
                [
                    527.24951171875,
                    487.42999267578125
                ]
            ],
            "group_id": null,
            "description": "",
            "shape_type": "rectangle",
            "flags": {},
            "mask": null
        },
        {
            "label": "motorcycle",
            "points": [
                [
                    881.3917236328125,
                    417.8966064453125
                ],
                [
                    934.7171630859375,
                    489.3939208984375
                ]
            ],
            "group_id": null,
            "description": "",
            "shape_type": "rectangle",
            "flags": {},
            "mask": null
        },
        {
            "label": "motorcycle",
            "points": [
                [
                    465.23516845703125,
                    409.7928466796875
                ],
                [
                    530.0335083007812,
                    509.2034912109375
                ]
            ],
            "group_id": null,
            "description": "",
            "shape_type": "rectangle",
            "flags": {},
            "mask": null
        },
        {
            "label": "rider",
            "points": [
                [
                    884.5340576171875,
                    384.95501708984375
                ],
                [
                    933.623779296875,
                    473.35772705078125
                ]
            ],
            "group_id": null,
            "description": "",
            "shape_type": "rectangle",
            "flags": {},
            "mask": null
        },
        {
            "label": "car",
            "points": [
                [
                    691.2087189205109,
                    394.9731750488281
                ],
                [
                    755.9306427486359,
                    453.0102233886719
                ]
            ],
            "group_id": null,
            "description": "",
            "shape_type": "rectangle",
            "flags": {},
            "mask": null
        },
        {
            "label": "car",
            "points": [
                [
                    537.240464952257,
                    363.2271433027964
                ],
                [
                    618.5714285714286,
                    456.42857142857144
                ]
            ],
            "group_id": null,
            "description": "",
            "shape_type": "rectangle",
            "flags": {},
            "mask": null
        }
    ],
    "imagePath": "Sequence_Day_10_frame_14850.jpg",
    "imageData": null,
    "imageHeight": 720,
    "imageWidth": 1280
}