{
    "version": "5.4.1",
    "flags": {},
    "shapes": [
        {
            "label": "car",
            "points": [
                [
                    0.228179931640625,
                    316.5841064453125
                ],
                [
                    392.20306396484375,
                    599.0256958007812
                ]
            ],
            "group_id": null,
            "description": "",
            "shape_type": "rectangle",
            "flags": {},
            "mask": null
        },
        {
            "label": "person",
            "points": [
                [
                    105.57681274414062,
                    240.70867919921875
                ],
                [
                    155.73150634765625,
                    318.26324462890625
                ]
            ],
            "group_id": null,
            "description": "",
            "shape_type": "rectangle",
            "flags": {},
            "mask": null
        },
        {
            "label": "person",
            "points": [
                [
                    39.84881591796875,
                    239.14178466796875
                ],
                [
                    95.67486572265625,
                    321.68988037109375
                ]
            ],
            "group_id": null,
            "description": "",
            "shape_type": "rectangle",
            "flags": {},
            "mask": null
        },
        {
            "label": "car",
            "points": [
                [
                    471.12225341796875,
                    380.9197998046875
                ],
                [
                    499.26483154296875,
                    404.2196044921875
                ]
            ],
            "group_id": null,
            "description": "",
            "shape_type": "rectangle",
            "flags": {},
            "mask": null
        },
        {
            "label": "person",
            "points": [
                [
                    0.01302337646484375,
                    238.1536865234375
                ],
                [
                    42.81005096435547,
                    331.4053955078125
                ]
            ],
            "group_id": null,
            "description": "",
            "shape_type": "rectangle",
            "flags": {},
            "mask": null
        }
    ],
    "imagePath": "Sequence_Day_6_frame_16650.jpg",
    "imageData": null,
    "imageHeight": 720,
    "imageWidth": 1280
}