{
    "version": "5.4.1",
    "flags": {},
    "shapes": [
        {
            "label": "bus",
            "points": [
                [
                    211.48550415039062,
                    275.6417236328125
                ],
                [
                    338.0144958496094,
                    428.1678466796875
                ]
            ],
            "group_id": null,
            "description": "",
            "shape_type": "rectangle",
            "flags": {},
            "mask": null
        }
    ],
    "imagePath": "Sequence_Night_15_frame_3570.jpg",
    "imageData": null,
    "imageHeight": 720,
    "imageWidth": 1280
}