{
    "version": "5.6.0",
    "flags": {},
    "shapes": [
        {
            "label": "car",
            "points": [
                [
                    858.3421020507812,
                    366.8546142578125
                ],
                [
                    969.1825561523438,
                    432.45770263671875
                ]
            ],
            "group_id": null,
            "description": "",
            "shape_type": "rectangle",
            "flags": {},
            "mask": null
        },
        {
            "label": "rickshaw",
            "points": [
                [
                    126.33287048339844,
                    329.37335205078125
                ],
                [
                    251.7346954345703,
                    452.24932861328125
                ]
            ],
            "group_id": null,
            "description": "",
            "shape_type": "rectangle",
            "flags": {},
            "mask": null
        },
        {
            "label": "truck",
            "points": [
                [
                    475.3446350097656,
                    340.1853332519531
                ],
                [
                    504.0321960449219,
                    379.5614929199219
                ]
            ],
            "group_id": null,
            "description": "",
            "shape_type": "rectangle",
            "flags": {},
            "mask": null
        },
        {
            "label": "truck",
            "points": [
                [
                    681.78271484375,
                    281.069091796875
                ],
                [
                    841.552001953125,
                    411.228271484375
                ]
            ],
            "group_id": null,
            "description": "",
            "shape_type": "rectangle",
            "flags": {},
            "mask": null
        },
        {
            "label": "bus",
            "points": [
                [
                    682.0614013671875,
                    281.2762451171875
                ],
                [
                    842.2110595703125,
                    411.33251953125
                ]
            ],
            "group_id": null,
            "description": "",
            "shape_type": "rectangle",
            "flags": {},
            "mask": null
        },
        {
            "label": "traffic sign",
            "points": [
                [
                    136.61920166015625,
                    309.644775390625
                ],
                [
                    207.01144409179688,
                    328.404296875
                ]
            ],
            "group_id": null,
            "description": "",
            "shape_type": "rectangle",
            "flags": {},
            "mask": null
        },
        {
            "label": "traffic sign",
            "points": [
                [
                    759.4599609375,
                    200.13909912109375
                ],
                [
                    783.635986328125,
                    232.04037475585938
                ]
            ],
            "group_id": null,
            "description": "",
            "shape_type": "rectangle",
            "flags": {},
            "mask": null
        }
    ],
    "imagePath": "Sequence_Day_4_frame_21810.jpg",
    "imageData": null,
    "imageHeight": 720,
    "imageWidth": 1280
}