{
    "version": "5.6.0",
    "flags": {},
    "shapes": [
        {
            "label": "person",
            "points": [
                [
                    33.619773864746094,
                    384.64239501953125
                ],
                [
                    81.32964324951172,
                    486.67572021484375
                ]
            ],
            "group_id": null,
            "description": "",
            "shape_type": "rectangle",
            "flags": {},
            "mask": null
        },
        {
            "label": "motorcycle",
            "points": [
                [
                    488.14434814453125,
                    383.1099853515625
                ],
                [
                    509.52593994140625,
                    417.099365234375
                ]
            ],
            "group_id": null,
            "description": "",
            "shape_type": "rectangle",
            "flags": {},
            "mask": null
        },
        {
            "label": "rider",
            "points": [
                [
                    447.87554931640625,
                    376.1837463378906
                ],
                [
                    466.73382568359375,
                    421.1255798339844
                ]
            ],
            "group_id": null,
            "description": "",
            "shape_type": "rectangle",
            "flags": {},
            "mask": null
        },
        {
            "label": "motorcycle",
            "points": [
                [
                    448.26947021484375,
                    389.7974853515625
                ],
                [
                    466.32464599609375,
                    423.3831787109375
                ]
            ],
            "group_id": null,
            "description": "",
            "shape_type": "rectangle",
            "flags": {},
            "mask": null
        },
        {
            "label": "motorcycle",
            "points": [
                [
                    171.75607299804688,
                    394.5708923339844
                ],
                [
                    229.69931030273438,
                    470.8788757324219
                ]
            ],
            "group_id": null,
            "description": "",
            "shape_type": "rectangle",
            "flags": {},
            "mask": null
        },
        {
            "label": "truck",
            "points": [
                [
                    559.829833984375,
                    20.316650390625
                ],
                [
                    1018.3753662109375,
                    575.8880004882812
                ]
            ],
            "group_id": null,
            "description": "",
            "shape_type": "rectangle",
            "flags": {},
            "mask": null
        },
        {
            "label": "motorcycle",
            "points": [
                [
                    447.8452453613281,
                    377.6385498046875
                ],
                [
                    466.9411926269531,
                    421.896728515625
                ]
            ],
            "group_id": null,
            "description": "",
            "shape_type": "rectangle",
            "flags": {},
            "mask": null
        }
    ],
    "imagePath": "Sequence_Day_4_frame_12900.jpg",
    "imageData": null,
    "imageHeight": 720,
    "imageWidth": 1280
}