{
    "version": "5.6.0",
    "flags": {},
    "shapes": [
        {
            "label": "motorcycle",
            "points": [
                [
                    63.67388916015625,
                    434.58660888671875
                ],
                [
                    329.908447265625,
                    714.1702270507812
                ]
            ],
            "group_id": null,
            "description": "",
            "shape_type": "rectangle",
            "flags": {},
            "mask": null
        },
        {
            "label": "truck",
            "points": [
                [
                    277.71429443359375,
                    195.42578125
                ],
                [
                    593.4398193359375,
                    505.3187255859375
                ]
            ],
            "group_id": null,
            "description": "",
            "shape_type": "rectangle",
            "flags": {},
            "mask": null
        },
        {
            "label": "rider",
            "points": [
                [
                    125.52428436279297,
                    335.52606201171875
                ],
                [
                    324.01580810546875,
                    630.63720703125
                ]
            ],
            "group_id": null,
            "description": "",
            "shape_type": "rectangle",
            "flags": {},
            "mask": null
        },
        {
            "label": "truck",
            "points": [
                [
                    638.0379638671875,
                    348.88726806640625
                ],
                [
                    721.051025390625,
                    419.53289794921875
                ]
            ],
            "group_id": null,
            "description": "",
            "shape_type": "rectangle",
            "flags": {},
            "mask": null
        },
        {
            "label": "rider",
            "points": [
                [
                    555.9725341796875,
                    387.7138671875
                ],
                [
                    612.8760986328125,
                    499.0374755859375
                ]
            ],
            "group_id": null,
            "description": "",
            "shape_type": "rectangle",
            "flags": {},
            "mask": null
        },
        {
            "label": "rider",
            "points": [
                [
                    456.4658203125,
                    383.36163330078125
                ],
                [
                    536.78759765625,
                    528.4296264648438
                ]
            ],
            "group_id": null,
            "description": "",
            "shape_type": "rectangle",
            "flags": {},
            "mask": null
        },
        {
            "label": "motorcycle",
            "points": [
                [
                    444.0452880859375,
                    418.70648193359375
                ],
                [
                    549.6614990234375,
                    573.1834106445312
                ]
            ],
            "group_id": null,
            "description": "",
            "shape_type": "rectangle",
            "flags": {},
            "mask": null
        },
        {
            "label": "car",
            "points": [
                [
                    666.214599609375,
                    395.39788818359375
                ],
                [
                    931.215087890625,
                    617.9909057617188
                ]
            ],
            "group_id": null,
            "description": "",
            "shape_type": "rectangle",
            "flags": {},
            "mask": null
        },
        {
            "label": "car",
            "points": [
                [
                    1108.37060546875,
                    398.25823974609375
                ],
                [
                    1280.0,
                    576.5484619140625
                ]
            ],
            "group_id": null,
            "description": "",
            "shape_type": "rectangle",
            "flags": {},
            "mask": null
        },
        {
            "label": "motorcycle",
            "points": [
                [
                    556.101318359375,
                    429.17333984375
                ],
                [
                    612.2862548828125,
                    527.4007568359375
                ]
            ],
            "group_id": null,
            "description": "",
            "shape_type": "rectangle",
            "flags": {},
            "mask": null
        },
        {
            "label": "motorcycle",
            "points": [
                [
                    647.1424560546875,
                    420.95758056640625
                ],
                [
                    695.7171630859375,
                    501.0816650390625
                ]
            ],
            "group_id": null,
            "description": "",
            "shape_type": "rectangle",
            "flags": {},
            "mask": null
        },
        {
            "label": "traffic sign",
            "points": [
                [
                    1190.8620689655172,
                    288.01724137931035
                ],
                [
                    1264.1379310344828,
                    359.5689655172414
                ]
            ],
            "group_id": null,
            "description": "",
            "shape_type": "rectangle",
            "flags": {},
            "mask": null
        },
        {
            "label": "truck",
            "points": [
                [
                    1061.5517241379312,
                    325.08620689655174
                ],
                [
                    1214.1379310344828,
                    419.05172413793105
                ]
            ],
            "group_id": null,
            "description": "",
            "shape_type": "rectangle",
            "flags": {},
            "mask": null
        }
    ],
    "imagePath": "Sequence_Day_16_frame_28830.jpg",
    "imageData": null,
    "imageHeight": 720,
    "imageWidth": 1280
}