{
    "version": "5.4.1",
    "flags": {},
    "shapes": [
        {
            "label": "truck",
            "points": [
                [
                    739.9456787109375,
                    257.10076904296875
                ],
                [
                    1109.786376953125,
                    674.9226684570312
                ]
            ],
            "group_id": null,
            "description": "",
            "shape_type": "rectangle",
            "flags": {},
            "mask": null
        },
        {
            "label": "car",
            "points": [
                [
                    0.308013916015625,
                    349.2060241699219
                ],
                [
                    505.4230041503906,
                    659.17431640625
                ]
            ],
            "group_id": null,
            "description": "",
            "shape_type": "rectangle",
            "flags": {},
            "mask": null
        },
        {
            "label": "car",
            "points": [
                [
                    450.7072448730469,
                    405.73455810546875
                ],
                [
                    588.19140625,
                    523.348388671875
                ]
            ],
            "group_id": null,
            "description": "",
            "shape_type": "rectangle",
            "flags": {},
            "mask": null
        },
        {
            "label": "car",
            "points": [
                [
                    583.06982421875,
                    403.533203125
                ],
                [
                    750.9814453125,
                    535.0875244140625
                ]
            ],
            "group_id": null,
            "description": "",
            "shape_type": "rectangle",
            "flags": {},
            "mask": null
        },
        {
            "label": "car",
            "points": [
                [
                    1184.2591552734375,
                    388.0487060546875
                ],
                [
                    1279.9188232421875,
                    560.9307861328125
                ]
            ],
            "group_id": null,
            "description": "",
            "shape_type": "rectangle",
            "flags": {},
            "mask": null
        },
        {
            "label": "car",
            "points": [
                [
                    1110.8251953125,
                    397.5264892578125
                ],
                [
                    1222.05859375,
                    514.0596923828125
                ]
            ],
            "group_id": null,
            "description": "",
            "shape_type": "rectangle",
            "flags": {},
            "mask": null
        }
    ],
    "imagePath": "Sequence_Day_16_frame_21420.jpg",
    "imageData": null,
    "imageHeight": 720,
    "imageWidth": 1280
}