{
    "version": "5.6.0",
    "flags": {},
    "shapes": [
        {
            "label": "motorcycle",
            "points": [
                [
                    296.6572265625,
                    474.0864562988281
                ],
                [
                    557.8931274414062,
                    720.0
                ]
            ],
            "group_id": null,
            "description": "",
            "shape_type": "rectangle",
            "flags": {},
            "mask": null
        },
        {
            "label": "rider",
            "points": [
                [
                    306.27105712890625,
                    340.2507629394531
                ],
                [
                    553.6837768554688,
                    669.1416015625
                ]
            ],
            "group_id": null,
            "description": "",
            "shape_type": "rectangle",
            "flags": {},
            "mask": null
        },
        {
            "label": "car",
            "points": [
                [
                    836.1743774414062,
                    378.3271179199219
                ],
                [
                    1280.0,
                    717.555419921875
                ]
            ],
            "group_id": null,
            "description": "",
            "shape_type": "rectangle",
            "flags": {},
            "mask": null
        },
        {
            "label": "person",
            "points": [
                [
                    343.6053466796875,
                    363.09033203125
                ],
                [
                    382.8192138671875,
                    410.906005859375
                ]
            ],
            "group_id": null,
            "description": "",
            "shape_type": "rectangle",
            "flags": {},
            "mask": null
        },
        {
            "label": "rider",
            "points": [
                [
                    643.1365966796875,
                    370.3388671875
                ],
                [
                    728.7540283203125,
                    546.3650512695312
                ]
            ],
            "group_id": null,
            "description": "",
            "shape_type": "rectangle",
            "flags": {},
            "mask": null
        },
        {
            "label": "motorcycle",
            "points": [
                [
                    0.0,
                    389.8603515625
                ],
                [
                    217.02316284179688,
                    619.8917236328125
                ]
            ],
            "group_id": null,
            "description": "",
            "shape_type": "rectangle",
            "flags": {},
            "mask": null
        },
        {
            "label": "motorcycle",
            "points": [
                [
                    0.03533935546875,
                    389.8922119140625
                ],
                [
                    128.56832885742188,
                    620.14990234375
                ]
            ],
            "group_id": null,
            "description": "",
            "shape_type": "rectangle",
            "flags": {},
            "mask": null
        },
        {
            "label": "motorcycle",
            "points": [
                [
                    85.446533203125,
                    426.7615051269531
                ],
                [
                    216.67092895507812,
                    587.724853515625
                ]
            ],
            "group_id": null,
            "description": "",
            "shape_type": "rectangle",
            "flags": {},
            "mask": null
        },
        {
            "label": "motorcycle",
            "points": [
                [
                    638.3373413085938,
                    437.41302490234375
                ],
                [
                    731.6132202148438,
                    584.4462280273438
                ]
            ],
            "group_id": null,
            "description": "",
            "shape_type": "rectangle",
            "flags": {},
            "mask": null
        },
        {
            "label": "rickshaw",
            "points": [
                [
                    463.1404958677686,
                    355.45454545454544
                ],
                [
                    610.2479338842975,
                    524.0495867768595
                ]
            ],
            "group_id": null,
            "description": "",
            "shape_type": "rectangle",
            "flags": {},
            "mask": null
        }
    ],
    "imagePath": "Sequence_Day_16_frame_28200.jpg",
    "imageData": null,
    "imageHeight": 720,
    "imageWidth": 1280
}