{
    "version": "5.5.0",
    "flags": {},
    "shapes": [
        {
            "label": "truck",
            "points": [
                [
                    557.140380859375,
                    351.42913818359375
                ],
                [
                    589.13427734375,
                    395.47625732421875
                ]
            ],
            "group_id": null,
            "description": "",
            "shape_type": "rectangle",
            "flags": {},
            "mask": null
        },
        {
            "label": "car",
            "points": [
                [
                    606.334228515625,
                    371.94256591796875
                ],
                [
                    624.708251953125,
                    388.22052001953125
                ]
            ],
            "group_id": null,
            "description": "",
            "shape_type": "rectangle",
            "flags": {},
            "mask": null
        },
        {
            "label": "traffic sign",
            "points": [
                [
                    119.47454833984375,
                    358.11865234375
                ],
                [
                    193.596435546875,
                    382.846435546875
                ]
            ],
            "group_id": null,
            "description": "",
            "shape_type": "rectangle",
            "flags": {},
            "mask": null
        },
        {
            "label": "traffic sign",
            "points": [
                [
                    362.52667236328125,
                    296.25469970703125
                ],
                [
                    485.26708984375,
                    379.06500244140625
                ]
            ],
            "group_id": null,
            "description": "",
            "shape_type": "rectangle",
            "flags": {},
            "mask": null
        },
        {
            "label": "truck",
            "points": [
                [
                    990.9259259259259,
                    420.1851851851852
                ],
                [
                    831.6666666666666,
                    312.7777777777778
                ]
            ],
            "group_id": null,
            "description": "",
            "shape_type": "rectangle",
            "flags": {},
            "mask": null
        }
    ],
    "imagePath": "Sequence_Day_5_frame_2310.jpg",
    "imageData": null,
    "imageHeight": 720,
    "imageWidth": 1280
}