{
    "version": "5.5.0",
    "flags": {},
    "shapes": [
        {
            "label": "truck",
            "points": [
                [
                    151.0257568359375,
                    100.85971069335938
                ],
                [
                    508.3609619140625,
                    468.3552551269531
                ]
            ],
            "group_id": null,
            "description": "",
            "shape_type": "rectangle",
            "flags": {},
            "mask": null
        },
        {
            "label": "person",
            "points": [
                [
                    1214.77587890625,
                    366.21484375
                ],
                [
                    1249.61279296875,
                    422.014404296875
                ]
            ],
            "group_id": null,
            "description": "",
            "shape_type": "rectangle",
            "flags": {},
            "mask": null
        },
        {
            "label": "car",
            "points": [
                [
                    612.1563720703125,
                    376.1111755371094
                ],
                [
                    640.9564208984375,
                    404.3049011230469
                ]
            ],
            "group_id": null,
            "description": "",
            "shape_type": "rectangle",
            "flags": {},
            "mask": null
        },
        {
            "label": "car",
            "points": [
                [
                    507.1341247558594,
                    375.8840026855469
                ],
                [
                    537.5885009765625,
                    394.4927673339844
                ]
            ],
            "group_id": null,
            "description": "",
            "shape_type": "rectangle",
            "flags": {},
            "mask": null
        },
        {
            "label": "car",
            "points": [
                [
                    557.5925925925926,
                    362.7777777777777
                ],
                [
                    587.2222222222223,
                    407.2222222222223
                ]
            ],
            "group_id": null,
            "description": "",
            "shape_type": "rectangle",
            "flags": {},
            "mask": null
        }
    ],
    "imagePath": "Sequence_Day_5_frame_5250.jpg",
    "imageData": null,
    "imageHeight": 720,
    "imageWidth": 1280
}