{
    "version": "5.5.0",
    "flags": {},
    "shapes": [
        {
            "label": "truck",
            "points": [
                [
                    640.936279296875,
                    344.9367370605469
                ],
                [
                    664.269287109375,
                    374.4908752441406
                ]
            ],
            "group_id": null,
            "description": "",
            "shape_type": "rectangle",
            "flags": {},
            "mask": null
        },
        {
            "label": "car",
            "points": [
                [
                    511.4222412109375,
                    357.42108154296875
                ],
                [
                    558.5230712890625,
                    412.49102783203125
                ]
            ],
            "group_id": null,
            "description": "",
            "shape_type": "rectangle",
            "flags": {},
            "mask": null
        },
        {
            "label": "motorcycle",
            "points": [
                [
                    433.86663818359375,
                    363.990478515625
                ],
                [
                    480.99395751953125,
                    443.0084228515625
                ]
            ],
            "group_id": null,
            "description": "",
            "shape_type": "rectangle",
            "flags": {},
            "mask": null
        }
    ],
    "imagePath": "Sequence_Day_5_frame_6210.jpg",
    "imageData": null,
    "imageHeight": 720,
    "imageWidth": 1280
}