{
    "version": "5.4.1",
    "flags": {},
    "shapes": [
        {
            "label": "rider",
            "points": [
                [
                    333.01983642578125,
                    381.0440673828125
                ],
                [
                    418.65728759765625,
                    488.9471435546875
                ]
            ],
            "group_id": null,
            "description": "",
            "shape_type": "rectangle",
            "flags": {},
            "mask": null
        },
        {
            "label": "motorcycle",
            "points": [
                [
                    339.683349609375,
                    417.86322021484375
                ],
                [
                    421.1517333984375,
                    522.6207275390625
                ]
            ],
            "group_id": null,
            "description": "",
            "shape_type": "rectangle",
            "flags": {},
            "mask": null
        }
    ],
    "imagePath": "Sequence_Day_5_frame_7440.jpg",
    "imageData": null,
    "imageHeight": 720,
    "imageWidth": 1280
}